gnani_rest_api/__init__.py
gnani_rest_api/client.py
gnani_rest_api/audio/__init__.py
gnani_asr_rest_api-0.0.2.dist-info/METADATA
gnani_asr_rest_api-0.0.2.dist-info/WHEEL
gnani_asr_rest_api-0.0.2.dist-info/top_level.txt
gnani_asr_rest_api-0.0.2.dist-info/RECORD
