Metadata-Version: 2.1
Name: gnani-asr-rest-api
Version: 0.0.2
Summary: gnani_asr_rest_api
Home-page: UNKNOWN
Author: gnani.ai
Author-email: <api.service@gnani.ai>
License: UNKNOWN
Keywords: python,automatic text to speech
Platform: UNKNOWN
Classifier: Development Status :: 3 - Alpha
Classifier: Intended Audience :: Education
Classifier: Programming Language :: Python :: 2
Classifier: Programming Language :: Python :: 3
Classifier: Operating System :: MacOS :: MacOS X
Classifier: Operating System :: Microsoft :: Windows
Requires-Dist: requests
